pymtl3_net/__init__.py
pymtl3_net/bflynet/BflyNetworkRTL.py
pymtl3_net/bflynet/BflyRouterRTL.py
pymtl3_net/bflynet/DTRBflyRouteUnitRTL.py
pymtl3_net/bflynet/__init__.py
pymtl3_net/bflynet/test/BflyNetworkRTL_test.py
pymtl3_net/bflynet/test/__init__.py
pymtl3_net/channel/ChannelCL.py
pymtl3_net/channel/ChannelRTL.py
pymtl3_net/channel/__init__.py
pymtl3_net/channel/test/ChannelCL_test.py
pymtl3_net/channel/test/ChannelRTL_test.py
pymtl3_net/channel/test/__init__.py
pymtl3_net/cmeshnet/CMeshNetworkRTL.py
pymtl3_net/cmeshnet/CMeshRouterRTL.py
pymtl3_net/cmeshnet/DORXCMeshRouteUnitRTL.py
pymtl3_net/cmeshnet/DORYCMeshRouteUnitRTL.py
pymtl3_net/cmeshnet/__init__.py
pymtl3_net/cmeshnet/directions.py
pymtl3_net/meshnet/DORXMeshRouteUnitCL.py
pymtl3_net/meshnet/DORXMeshRouteUnitRTL.py
pymtl3_net/meshnet/DORYMeshRouteUnitCL.py
pymtl3_net/meshnet/DORYMeshRouteUnitRTL.py
pymtl3_net/meshnet/MeshNetworkCL.py
pymtl3_net/meshnet/MeshNetworkMflitRTL.py
pymtl3_net/meshnet/MeshNetworkRTL.py
pymtl3_net/meshnet/MeshRouteUnitRTLMflitXY.py
pymtl3_net/meshnet/MeshRouterCL.py
pymtl3_net/meshnet/MeshRouterFL.py
pymtl3_net/meshnet/MeshRouterMflitRTL.py
pymtl3_net/meshnet/MeshRouterRTL.py
pymtl3_net/meshnet/__init__.py
pymtl3_net/meshnet/directions.py
pymtl3_net/meshnet/test/DORYMeshRouteUnitRTL_test.py
pymtl3_net/meshnet/test/MeshNetworkCL_test.py
pymtl3_net/meshnet/test/MeshNetworkMflitRTL_test.py
pymtl3_net/meshnet/test/MeshNetworkRTL_test.py
pymtl3_net/meshnet/test/MeshRouteUnitRTLMflitXY_test.py
pymtl3_net/meshnet/test/MeshRouterCL_test.py
pymtl3_net/meshnet/test/MeshRouterMflitRTL_test.py
pymtl3_net/meshnet/test/MeshRouterRTL_test.py
pymtl3_net/meshnet/test/__init__.py
pymtl3_net/meshnet/test/test_helpers.py
pymtl3_net/mmxbar/MasterMinionXbarGeneric.py
pymtl3_net/mmxbar/Table.py
pymtl3_net/mmxbar/__init__.py
pymtl3_net/mmxbar/adapters.py
pymtl3_net/mmxbar/msg_types.py
pymtl3_net/mmxbar/test/MasterMinionXbarGeneric_test.py
pymtl3_net/mmxbar/test/Table_test.py
pymtl3_net-0.9.0.dist-info/LICENSE
pymtl3_net-0.9.0.dist-info/METADATA
pymtl3_net-0.9.0.dist-info/WHEEL
pymtl3_net-0.9.0.dist-info/top_level.txt
pymtl3_net-0.9.0.dist-info/RECORD
