Metadata-Version: 2.1
Name: pymtl3-net
Version: 0.9.0
Summary: PyMTL3-Net: an open-source Python-based framework for modeling, testing, and evaluating on-chip interconnection networks
Home-page: https://github.com/cornell-brg/pymtl3-net
Author: Batten Research Group
Author-email: brg-pymtl@csl.cornell.edu
License: BSD
Platform: UNKNOWN
Classifier: Development Status :: 4 - Beta
Classifier: License :: OSI Approved :: BSD License
Classifier: Programming Language :: Python :: 3 :: Only
Classifier: Operating System :: MacOS :: MacOS X
Classifier: Operating System :: POSIX :: Linux
Classifier: Topic :: Scientific/Engineering :: Electronic Design Automation (EDA)
Requires-Python: >=3.7
